baguette/__init__.py
baguette/baguette.py
baguette/logger.py
baguette/rack.py
baguette/bakery/__init__.py
baguette/bakery/bake.py
baguette/bakery/compiler.py
baguette/bakery/source/__init__.py
baguette/bakery/source/build.py
baguette/bakery/source/colors.py
baguette/bakery/source/config.py
baguette/bakery/source/event.py
baguette/bakery/source/filters.py
baguette/bakery/source/graph.py
baguette/bakery/source/record.py
baguette/bakery/source/utils.py
baguette/bakery/source/parsers/__init__.py
baguette/bakery/source/parsers/abc.py
baguette/bakery/source/parsers/utils.py
baguette/bakery/source/parsers/lib/__init__.py
baguette/bakery/source/parsers/lib/cuckoo.py
baguette/bakery/source/types/__init__.py
baguette/bakery/source/types/utils.py
baguette/bakery/source/types/data/__init__.py
baguette/bakery/source/types/data/__proc__.py
baguette/bakery/source/types/data/entities.py
baguette/bakery/source/types/data/integration.py
baguette/bakery/source/types/data/relations.py
baguette/bakery/source/types/data/utils.py
baguette/bakery/source/types/execution/__init__.py
baguette/bakery/source/types/execution/__proc__.py
baguette/bakery/source/types/execution/entities.py
baguette/bakery/source/types/execution/integration.py
baguette/bakery/source/types/execution/relations.py
baguette/bakery/source/types/execution/utils.py
baguette/bakery/source/types/filesystem/__init__.py
baguette/bakery/source/types/filesystem/__proc__.py
baguette/bakery/source/types/filesystem/entities.py
baguette/bakery/source/types/filesystem/integration.py
baguette/bakery/source/types/filesystem/relations.py
baguette/bakery/source/types/imports/__init__.py
baguette/bakery/source/types/imports/__proc__.py
baguette/bakery/source/types/imports/entities.py
baguette/bakery/source/types/imports/integration.py
baguette/bakery/source/types/imports/relations.py
baguette/bakery/source/types/network/__init__.py
baguette/bakery/source/types/network/__proc__.py
baguette/bakery/source/types/network/entities.py
baguette_verse-1.8.8.dist-info/METADATA
baguette_verse-1.8.8.dist-info/WHEEL
baguette_verse-1.8.8.dist-info/entry_points.txt
baguette_verse-1.8.8.dist-info/licenses/LICENSE
baguette_verse-1.8.8.dist-info/RECORD
