Metadata-Version: 2.1
Name: baguette-verse
Version: 1.8.8
Summary: A malware behavioral analysis framework centered around BAGUETTE!
Project-URL: Repository, https://gitlab.inria.fr/vraulin/baguette-verse
Project-URL: Bug Tracker, https://gitlab.inria.fr/vraulin/baguette-verse/-/issues
Author-email: Vincent Raulin <vincent.raulin@inria.fr>
License:                     GNU AFFERO GENERAL PUBLIC LICENSE
License-File: LICENSE
Classifier: License :: OSI Approved :: GNU Affero General Public License v3
Classifier: Operating System :: OS Independent
Classifier: Programming Language :: Python :: 3
Requires-Python: >=3.11
Requires-Dist: boa-lib>=1.2
Requires-Dist: levenshtein
Requires-Dist: python-magic-bin; platform_system == 'Windows'
Requires-Dist: python-magic; platform_system != 'Windows'
Requires-Dist: viper-lib>=1.5.2
